LICENSE
chuy/__init__.py
chuy/__main__.py
chuy/core.py
chuy/helpers.py
chuy-1.4.0.dist-info/entry_points.txt
chuy-1.4.0.dist-info/LICENSE
chuy-1.4.0.dist-info/WHEEL
chuy-1.4.0.dist-info/METADATA
chuy-1.4.0.dist-info/RECORD
