Metadata-Version: 2.1
Name: chuy
Version: 1.4.0
Summary: Set alias to long commands and speed up your workflow.
Home-page: https://github.com/UltiRequiem/chuy
Keywords: commands,utilities,cli
Author: Eliaz Bobadilla
Author-email: eliaz.bobadilladev@gmail.com
Requires-Python: >=3.7,<4.0
Classifier: Programming Language :: Python :: 3
Classifier: Programming Language :: Python :: 3.7
Classifier: Programming Language :: Python :: 3.8
Classifier: Programming Language :: Python :: 3.9
Requires-Dist: colorama (>=0.4.4,<0.5.0)
Requires-Dist: colores (>=0.1.0,<0.2.0)
Requires-Dist: toml (>=0.10.2,<0.11.0)
Project-URL: Repository, https://github.com/UltiRequiem/chuy
